MANIFEST.in
TODO.txt
setup.cfg
setup.py
sample/MANIFEST.in
sample/buildout.cfg
sample/setup.py
src/buildout/__init__.py
src/buildout.packager.egg-info/.PKG-INFO.swp
src/buildout.packager.egg-info/PKG-INFO
src/buildout.packager.egg-info/SOURCES.txt
src/buildout.packager.egg-info/dependency_links.txt
src/buildout.packager.egg-info/entry_points.txt
src/buildout.packager.egg-info/requires.txt
src/buildout.packager.egg-info/top_level.txt
src/buildout/packager/README.txt
src/buildout/packager/__init__.py
src/buildout/packager/command/__init__.py
src/buildout/packager/command/bdist_buildout.py
src/buildout/packager/command/bdist_buildout_prepare.py
src/buildout/packager/command/bdist_buildout_unix.py
src/buildout/packager/command/bdist_buildout_win32.py
src/buildout/packager/command/packages/bootstrap2.py
src/buildout/packager/command/packages/buildout_post.cfg
src/buildout/packager/command/packages/buildout_pre.cfg
src/buildout/packager/command/packages/distribute_setup.py
src/buildout/packager/command/packages/ez_setup.py
src/buildout/packager/command/packages/postinstall.py