Metadata-Version: 1.0
Name: buildout.packager
Version: 0.0.1dev-r662
Summary: buildout.packager generate installer from setup.py and buildout.cfg files.
Home-page: http://svn.freia.jp/open/buildout.packager/
Author: Takayuki SHIMIZUKAWA
Author-email: shimizukawa at gmail.com
License: PSL
Keywords: zc.buildout,installer
Platform: UNKNOWN
Classifier: Development Status :: 4 - Beta
Classifier: Intended Audience :: Developers
Classifier: License :: OSI Approved :: Python Software Foundation License
Classifier: Programming Language :: Python
Classifier: Topic :: Software Development :: Build Tools
Classifier: Topic :: Software Development :: Libraries :: Python Modules
